qft/__init__.py
qft/hmc.py
qft/metropolis.py
qft-0.0.3.dist-info/WHEEL
qft-0.0.3.dist-info/METADATA
qft-0.0.3.dist-info/RECORD
